langmo/__init__.py
langmo/_version.py
langmo/base.py
langmo/checkpoint.py
langmo/data.py
langmo/evaluate.py
langmo/generate.py
langmo/log_helper.py
langmo/logger_dummy.py
langmo/main.py
langmo/model.py
langmo/report.py
langmo/trainer.py
langmo/benchmarks/__init__.py
langmo/benchmarks/__main__.py
langmo/benchmarks/visualize.py
langmo/benchmarks/COPA/__init__.py
langmo/benchmarks/COPA/data.py
langmo/benchmarks/COPA/main.py
langmo/benchmarks/COPA/model.py
langmo/benchmarks/FillMask/__init__.py
langmo/benchmarks/FillMask/__main__.py
langmo/benchmarks/NLI/__init__.py
langmo/benchmarks/NLI/__main__.py
langmo/benchmarks/NLI/data.py
langmo/benchmarks/NLI/model.py
langmo/callbacks/__init__.py
langmo/callbacks/layernorm.py
langmo/callbacks/model_snapshots_schedule.py
langmo/callbacks/monitor.py
langmo/config/__init__.py
langmo/config/base.py
langmo/config/glue.py
langmo/config/pretrain.py
langmo/nn/__init__.py
langmo/nn/classifier.py
langmo/nn/cnet.py
langmo/nn/heads.py
langmo/nn/siamese.py
langmo/nn/utils.py
langmo/nn/wrappers.py
langmo/training/__init__.py
langmo/training/base.py
langmo/training/base_data.py
langmo/training/glue/__init__.py
langmo/training/glue/__main__.py
langmo/training/glue/data.py
langmo/training/glue/model.py
langmo/training/mlm/__init__.py
langmo/training/mlm/__main__.py
langmo/training/mlm/data.py
langmo/training/mlm/plmodel.py
langmo/training/mlm/resume.py
langmo/training/multitask/__init__.py
langmo/training/multitask/__main__.py
langmo/training/multitask/config.py
langmo/training/multitask/data.py
langmo/training/multitask/model.py
langmo/training/qa/__init__.py
langmo/training/qa/__main__.py
langmo/training/qa/config.py
langmo/training/qa/data.py
langmo/training/qa/model.py
langmo/utils/__init__.py
langmo/utils/copy_logs.py
langmo/utils/distributed.py
langmo/utils/dynamic_import_module.py
langmo/utils/json_reader.py
langmo/utils/model_utils.py
langmo/utils/preprocess.py
langmo/utils/resolve_callbacks.py
langmo/utils/shuffle.py
langmo-0.2.0.dist-info/METADATA
langmo-0.2.0.dist-info/WHEEL
langmo-0.2.0.dist-info/top_level.txt
langmo-0.2.0.dist-info/RECORD
