Metadata-Version: 2.1
Name: langmo
Version: 0.2.0
Summary: toolbox for various tasks in the area of vector space models of computational linguistic
Home-page: http://vecto.space
Download-URL: 
Author: 
Author-email: 
Maintainer: 
Maintainer-email: 
License: Apache License 2.0
Keywords: NLP,linguistics,language
Classifier: Development Status :: 3 - Alpha
Classifier: Environment :: Console
Classifier: Intended Audience :: Science/Research
Classifier: License :: OSI Approved :: Apache Software License
Classifier: Natural Language :: English
Classifier: Operating System :: POSIX
Classifier: Programming Language :: Python :: 3.5
Classifier: Programming Language :: Python :: 3.6
Classifier: Programming Language :: Python :: 3 :: Only
Classifier: Topic :: Text Processing :: Linguistic
Requires-Python: >=3.5
Requires-Dist: kapral (>=0.1.2)
Requires-Dist: vecto
Requires-Dist: pytorch-lightning
Requires-Dist: datasets
Requires-Dist: transformers
Requires-Dist: protonn
Requires-Dist: wandb
Requires-Dist: humanfriendly
Requires-Dist: lightning
Requires-Dist: langdetect
